{
  "version": 2,
  "updated": "2026-07-24T03:49:54+08:00",
  "generator": {
    "mode": "github-auto-discovery",
    "searched": 100,
    "static_passed": 7,
    "verified": 6
  },
  "presets": [
    {
      "id": "z",
      "name": "Z.ini 完整版",
      "description": "稳定方案 · 完整分流，覆盖广告、流媒体、AI 服务与地区节点组。",
      "source_url": "https://raw.githubusercontent.com/bassdrum007/X/refs/heads/master/Z.ini",
      "source_repo": "bassdrum007/X",
      "recommended": true,
      "enabled": true,
      "discovered": false,
      "verified_at": "2026-07-24",
      "updated": "2026-07-24"
    },
    {
      "id": "zz",
      "name": "Zz.ini 精简版",
      "description": "稳定方案 · 精简代理组和规则数量，适合轻量与快速加载。",
      "source_url": "https://raw.githubusercontent.com/bassdrum007/X/refs/heads/master/Zz.ini",
      "source_repo": "bassdrum007/X",
      "recommended": false,
      "enabled": true,
      "discovered": false,
      "verified_at": "2026-07-24",
      "updated": "2026-07-24"
    },
    {
      "id": "auto-cutethotw-clashrule-back-71c9495",
      "name": "ClashRule · Back",
      "description": "自动发现并验证 · 7 条规则源 · 3 个代理组",
      "source_url": "https://raw.githubusercontent.com/cutethotw/ClashRule/refs/heads/main/Back.ini",
      "source_repo": "cutethotw/ClashRule",
      "source_path": "Back.ini",
      "stars": 916,
      "recommended": false,
      "enabled": true,
      "discovered": true,
      "verified_at": "2026-07-24",
      "updated": "2026-06-02"
    },
    {
      "id": "auto-xegony-clash-ini-cf-a44f8a7",
      "name": "Xegony · cf",
      "description": "自动发现并验证 · 53 条规则源 · 31 个代理组",
      "source_url": "https://raw.githubusercontent.com/Xegony/clash_ini/refs/heads/main/cf.ini",
      "source_repo": "Xegony/clash_ini",
      "source_path": "cf.ini",
      "stars": 0,
      "recommended": false,
      "enabled": true,
      "discovered": true,
      "verified_at": "2026-07-24",
      "updated": "2026-06-11"
    },
    {
      "id": "auto-xu348025782-csguize-ac-93628d7",
      "name": "csguize · AC",
      "description": "自动发现并验证 · 17 条规则源 · 16 个代理组",
      "source_url": "https://raw.githubusercontent.com/xu348025782/csguize/refs/heads/main/AC.ini",
      "source_repo": "xu348025782/csguize",
      "source_path": "AC.ini",
      "stars": 0,
      "recommended": false,
      "enabled": true,
      "discovered": true,
      "verified_at": "2026-07-24",
      "updated": "2026-07-14"
    },
    {
      "id": "auto-youzhi1233-rule-fuh5-ac7ce19",
      "name": "rule · fuh5",
      "description": "自动发现并验证 · 6 条规则源 · 11 个代理组",
      "source_url": "https://raw.githubusercontent.com/youzhi1233/rule/refs/heads/main/fuh5.ini",
      "source_repo": "youzhi1233/rule",
      "source_path": "fuh5.ini",
      "stars": 0,
      "recommended": false,
      "enabled": true,
      "discovered": true,
      "verified_at": "2026-07-24",
      "updated": "2026-06-06"
    },
    {
      "id": "auto-billyas-multicountry-aaai-cd6600a",
      "name": "multiCountry · aaai",
      "description": "自动发现并验证 · 12 条规则源 · 16 个代理组",
      "source_url": "https://raw.githubusercontent.com/Billyas/multiCountry/refs/heads/main/aaai.ini",
      "source_repo": "Billyas/multiCountry",
      "source_path": "aaai.ini",
      "stars": 0,
      "recommended": false,
      "enabled": true,
      "discovered": true,
      "verified_at": "2026-07-24",
      "updated": "2026-04-22"
    },
    {
      "id": "auto-ldsoy-clash-my-7a4bad1",
      "name": "ldsoy · My",
      "description": "自动发现并验证 · 13 条规则源 · 6 个代理组",
      "source_url": "https://raw.githubusercontent.com/ldsoy/Clash/refs/heads/main/My.ini",
      "source_repo": "ldsoy/Clash",
      "source_path": "My.ini",
      "stars": 0,
      "recommended": false,
      "enabled": true,
      "discovered": true,
      "verified_at": "2026-07-24",
      "updated": "2026-05-05"
    }
  ]
}
